MyAPIManager/MyAPIManager.py
MyAPIManager/__init__.py
MyAPIManager-0.0.1.dist-info/METADATA
MyAPIManager-0.0.1.dist-info/WHEEL
MyAPIManager-0.0.1.dist-info/top_level.txt
MyAPIManager-0.0.1.dist-info/RECORD
